setup.py
altin/__init__.py
altin/altin.py
altin.egg-info/PKG-INFO
altin.egg-info/SOURCES.txt
altin.egg-info/dependency_links.txt
altin.egg-info/entry_points.txt
altin.egg-info/top_level.txt