Metadata-Version: 1.1
Name: altin
Version: 0.0.5
Summary: Check last 30 days gold prices with email
Home-page: https://github.com/aydantasdemir/altin
Author: Aydan Tasdemir
Author-email: aydantasdemir@gmail.com
License: UNKNOWN
Platform: UNKNOWN
Classifier: Programming Language :: Python
Classifier: Programming Language :: Python :: 2
Classifier: License :: OSI Approved :: GNU General Public License (GPL)
Classifier: Operating System :: OS Independent
Classifier: Development Status :: 1 - Planning
Classifier: Environment :: Console
Classifier: Intended Audience :: Financial and Insurance Industry
Classifier: Topic :: Utilities
